specpulse/__init__.py
specpulse/__main__.py
specpulse/_version.py
specpulse/cli/__init__.py
specpulse/cli/main.py
specpulse/cli/monitor.py
specpulse/cli/commands/__init__.py
specpulse/cli/commands/feature_commands.py
specpulse/cli/commands/plan_task_commands.py
specpulse/cli/commands/project_commands.py
specpulse/cli/commands/sp_plan_commands.py
specpulse/cli/commands/sp_pulse_commands.py
specpulse/cli/commands/sp_spec_commands.py
specpulse/cli/commands/sp_task_commands.py
specpulse/cli/commands/spec_commands.py
specpulse/cli/handlers/__init__.py
specpulse/cli/handlers/command_handler.py
specpulse/cli/parsers/__init__.py
specpulse/cli/parsers/subcommand_parsers.py
specpulse/core/__init__.py
specpulse/core/ai_instruction_provider.py
specpulse/core/ai_integration.py
specpulse/core/async_validator.py
specpulse/core/checkpoints.py
specpulse/core/config_validator.py
specpulse/core/context_injector.py
specpulse/core/custom_validation.py
specpulse/core/decomposition_service.py
specpulse/core/feature_id_generator.py
specpulse/core/incremental.py
specpulse/core/interfaces.py
specpulse/core/memory_manager.py
specpulse/core/memory_provider.py
specpulse/core/notes_manager.py
specpulse/core/path_manager.py
specpulse/core/script_generator.py
specpulse/core/service_container.py
specpulse/core/specpulse.py
specpulse/core/template_cache.py
specpulse/core/template_manager.py
specpulse/core/template_provider.py
specpulse/core/tier_constants.py
specpulse/core/tier_manager.py
specpulse/core/validation_rules.py
specpulse/core/validator.py
specpulse/core/validators/__init__.py
specpulse/core/validators/plan_validator.py
specpulse/core/validators/sdd_validator.py
specpulse/core/validators/spec_validator.py
specpulse/models/__init__.py
specpulse/models/project_context.py
specpulse/monitor/__init__.py
specpulse/monitor/calculator.py
specpulse/monitor/display.py
specpulse/monitor/errors.py
specpulse/monitor/integration.py
specpulse/monitor/models.py
specpulse/monitor/state_manager.py
specpulse-2.6.2.dist-info/licenses/LICENSE
specpulse-2.6.2.dist-info/METADATA
specpulse-2.6.2.dist-info/WHEEL
specpulse-2.6.2.dist-info/entry_points.txt
specpulse-2.6.2.dist-info/top_level.txt
specpulse-2.6.2.dist-info/RECORD
