Metadata-Version: 2.4
Name: specpulse
Version: 2.6.2
Summary: SpecPulse v2.6.2 - AI-Enhanced Specification-Driven Development Framework with Advanced Task Monitoring and Real-time Analytics
Home-page: https://github.com/specpulse
Author: SpecPulse
Author-email: 
Maintainer: SpecPulse
License: MIT
Project-URL: Homepage, https://github.com/specpulse
Project-URL: Repository, https://github.com/specpulse/specpulse
Project-URL: Issues, https://github.com/specpulse/specpulse/issues
Project-URL: Documentation, https://github.com/specpulse/specpulse/wiki
Project-URL: Changelog, https://github.com/specpulse/specpulse/releases
Keywords: development,specification,ai,claude,gemini,automation,framework,cli,monitoring,task-tracking,progress-analytics,real-time
Classifier: Development Status :: 4 - Beta
Classifier: Intended Audience :: Developers
Classifier: Topic :: Software Development :: Build Tools
Classifier: Topic :: Software Development :: Code Generators
Classifier: Topic :: Software Development :: Documentation
Classifier: License :: OSI Approved :: MIT License
Classifier: Programming Language :: Python :: 3
Classifier: Programming Language :: Python :: 3.11
Classifier: Programming Language :: Python :: 3.12
Classifier: Programming Language :: Python :: 3.13
Classifier: Operating System :: OS Independent
Requires-Python: >=3.11
License-File: LICENSE
Requires-Dist: pyyaml<7.0,>=6.0
Requires-Dist: click<9.0,>=8.0
Requires-Dist: rich<14.0,>=13.0
Requires-Dist: jinja2<4.0,>=3.0
Requires-Dist: gitpython<4.0,>=3.1
Requires-Dist: toml<1.0,>=0.10
Requires-Dist: packaging<25.0,>=21.0
Provides-Extra: dev
Requires-Dist: pytest>=7.0; extra == "dev"
Requires-Dist: pytest-cov>=4.0; extra == "dev"
Requires-Dist: black>=23.0; extra == "dev"
Requires-Dist: flake8>=6.0; extra == "dev"
Requires-Dist: mypy>=1.0; extra == "dev"
Requires-Dist: pre-commit>=3.0; extra == "dev"
Dynamic: home-page
Dynamic: license-file
Dynamic: requires-python
